asyncpgx/__init__.py
asyncpgx/connection.py
asyncpgx/exceptions.py
asyncpgx/prepared_statement.py
asyncpgx/py.typed
asyncpgx/query.py
asyncpgx/tests/__init__.py
asyncpgx/tests/conftest.py
asyncpgx/tests/test_connection.py
asyncpgx/tests/test_query.py
asyncpgx-1.5.0.dist-info/LICENSE.md
asyncpgx-1.5.0.dist-info/WHEEL
asyncpgx-1.5.0.dist-info/METADATA
asyncpgx-1.5.0.dist-info/RECORD
