Metadata-Version: 2.1
Name: asyncpgx
Version: 1.5.0
Summary: User-friendly extensions for asyncpg
Home-page: https://github.com/laukhin/asyncpgx
License: Apache-2.0
Keywords: postgresql,asyncio,asyncpg
Author: Vladislav Laukhin
Author-email: laukhin97@gmail.com
Requires-Python: >=3.7.2,<3.12
Classifier: License :: OSI Approved :: Apache Software License
Classifier: Programming Language :: Python :: 3
Classifier: Programming Language :: Python :: 3.8
Classifier: Programming Language :: Python :: 3.9
Classifier: Programming Language :: Python :: 3.10
Classifier: Programming Language :: Python :: 3.11
Provides-Extra: format
Requires-Dist: asyncpg (>=0.21,<0.28)
Project-URL: Documentation, https://laukhin.github.io/asyncpgx/index.html
Project-URL: Repository, https://github.com/laukhin/asyncpgx
